README.md
setup.py
gitbarry/__init__.py
gitbarry/constants.py
gitbarry/main.py
gitbarry.egg-info/PKG-INFO
gitbarry.egg-info/SOURCES.txt
gitbarry.egg-info/dependency_links.txt
gitbarry.egg-info/entry_points.txt
gitbarry.egg-info/requires.txt
gitbarry.egg-info/top_level.txt
gitbarry/actions/__init__.py
gitbarry/actions/abstract.py
gitbarry/actions/merge.py
gitbarry/actions/open_browser.py
gitbarry/actions/pull_request.py
gitbarry/actions/tag.py
gitbarry/config/__init__.py
gitbarry/config/convert.py
gitbarry/config/exceptions.py
gitbarry/config/validator.py
gitbarry/reasons/__init__.py
gitbarry/reasons/abstract.py
gitbarry/reasons/finish.py
gitbarry/reasons/start.py
gitbarry/reasons/switch.py
gitbarry/utils/__init__.py
gitbarry/utils/git.py
gitbarry/utils/shortcuts.py
tests/__init__.py
tests/constants_test.py
tests/utils_git_test.py